pydicomsorter/__init__.py
pydicomsorter/cli.py
pydicomsorter/dicomsort.py
pydicomsorter/file_list.py
pydicomsorter/io.py
pydicomsorter/options.py
pydicomsorter/parser.py
pydicomsorter/tags4format.py
pydicomsorter/sandbox/__init__.py
pydicomsorter/sandbox/buildtree.py
pydicomsorter/sandbox/dicomsort.py
pydicomsorter/sandbox/diffwork.py
pydicomsorter-0.15.0.dist-info/METADATA
pydicomsorter-0.15.0.dist-info/WHEEL
pydicomsorter-0.15.0.dist-info/entry_points.txt
pydicomsorter-0.15.0.dist-info/licenses/LICENSE
pydicomsorter-0.15.0.dist-info/RECORD
