Metadata-Version: 2.3
Name: pydicomsorter
Version: 0.15.0
Summary: A Quick Tool For Sorting Dicom Files
Project-URL: homepage, https://github.com/jjjermiah/pydicomsorter
Project-URL: repository, https://github.com/jjjermiah/pydicomsorter
Project-URL: documentation, https://jjjermiah.github.io/pydicomsorter/
Project-URL: changelog, https://github.com/jjjermiah/pydicomsorter/blob/main/docs/CHANGELOG.md
Project-URL: issues, https://github.com/jjjermiah/pydicomsorter/issues
Author-email: Jermiah Joseph <jermiahjoseph98@gmail.com>
Maintainer-email: Jermiah Joseph <jermiahjoseph98@gmail.com>
License-Expression: MIT
License-File: LICENSE
Keywords: package,pixi,pydicomsorter,python
Classifier: License :: OSI Approved :: MIT License
Classifier: Natural Language :: English
Classifier: Operating System :: OS Independent
Classifier: Programming Language :: Python :: 3.10
Classifier: Programming Language :: Python :: 3.11
Classifier: Programming Language :: Python :: 3.12
Requires-Python: >=3.10
Requires-Dist: pydantic
Requires-Dist: pydicom
Requires-Dist: rich
Requires-Dist: rich-click
